dnxmy/__init__.py
dnxmy/config_generator.py
dnxmy/dnxmy.py
dnxmy/variable_generator.py
dnxmy-1.0.2.dist-info/LICENSE
dnxmy-1.0.2.dist-info/METADATA
dnxmy-1.0.2.dist-info/WHEEL
dnxmy-1.0.2.dist-info/top_level.txt
dnxmy-1.0.2.dist-info/RECORD
