Metadata-Version: 2.1
Name: dnxmy
Version: 1.0.2
Summary: dnxmy: dummy data generator for machine learning and statistics
Home-page: https://github.com/roseiricho/dnxmy
Author: Yuki Yamamoto
Author-email: curious.yamamon@gmail.com
Maintainer: Yuki Yamamoto
Maintainer-email: curious.yamamon@gmail.com
License: MIT License
Download-URL: https://github.com/roseiricho/dnxmy
Platform: UNKNOWN
Classifier: Intended Audience :: Science/Research
Classifier: License :: OSI Approved :: MIT License
Classifier: Programming Language :: Python :: 3
Classifier: Programming Language :: Python :: 3.6
Classifier: Programming Language :: Python :: 3.7
Classifier: Programming Language :: Python :: 3.8
Classifier: Programming Language :: Python :: 3.9
Classifier: Programming Language :: Python :: 3 :: Only
Classifier: Topic :: Scientific/Engineering
Requires-Python: >=3.6
Requires-Dist: numpy (>=1.22.4)
Requires-Dist: pandas (>=1.4.4)
